mech_utils/__init__.py
mech_utils/mech_utils.py
mech_utils-0.1.1.dist-info/METADATA
mech_utils-0.1.1.dist-info/WHEEL
mech_utils-0.1.1.dist-info/RECORD
