Metadata-Version: 2.4
Name: mech_utils
Version: 0.1.1
Summary: mech_2700_toolbox
Author-email: Ryan <cashconvertryan@gmail.com>
License-Expression: MIT
Requires-Python: >=3.8
